maap_algorithms_jupyter_extension/__init__.py
maap_algorithms_jupyter_extension/_version.py
maap_algorithms_jupyter_extension-0.4.0.data/data/share/jupyter/labextensions/maap_algorithms_jupyter_extension/package.json
maap_algorithms_jupyter_extension-0.4.0.data/data/share/jupyter/labextensions/maap_algorithms_jupyter_extension/static/146.d1b73a9a356525342fab.js
maap_algorithms_jupyter_extension-0.4.0.data/data/share/jupyter/labextensions/maap_algorithms_jupyter_extension/static/146.d1b73a9a356525342fab.js.LICENSE.txt
maap_algorithms_jupyter_extension-0.4.0.data/data/share/jupyter/labextensions/maap_algorithms_jupyter_extension/static/258.23f787ddb561616e46c2.js
maap_algorithms_jupyter_extension-0.4.0.data/data/share/jupyter/labextensions/maap_algorithms_jupyter_extension/static/336.e152dfc08954fe5101bb.js
maap_algorithms_jupyter_extension-0.4.0.data/data/share/jupyter/labextensions/maap_algorithms_jupyter_extension/static/359.1f3592a08fbc088d213e.js
maap_algorithms_jupyter_extension-0.4.0.data/data/share/jupyter/labextensions/maap_algorithms_jupyter_extension/static/361.cfad7220b9bd3e5fd875.js
maap_algorithms_jupyter_extension-0.4.0.data/data/share/jupyter/labextensions/maap_algorithms_jupyter_extension/static/361.cfad7220b9bd3e5fd875.js.LICENSE.txt
maap_algorithms_jupyter_extension-0.4.0.data/data/share/jupyter/labextensions/maap_algorithms_jupyter_extension/static/376.86ff66106247a561c134.js
maap_algorithms_jupyter_extension-0.4.0.data/data/share/jupyter/labextensions/maap_algorithms_jupyter_extension/static/376.86ff66106247a561c134.js.LICENSE.txt
maap_algorithms_jupyter_extension-0.4.0.data/data/share/jupyter/labextensions/maap_algorithms_jupyter_extension/static/477.7bd41c3494d6065cf63f.js
maap_algorithms_jupyter_extension-0.4.0.data/data/share/jupyter/labextensions/maap_algorithms_jupyter_extension/static/487.7b2ccaeeb2b22b659a0f.js
maap_algorithms_jupyter_extension-0.4.0.dist-info/METADATA
maap_algorithms_jupyter_extension-0.4.0.dist-info/WHEEL
maap_algorithms_jupyter_extension-0.4.0.dist-info/licenses/LICENSE
maap_algorithms_jupyter_extension-0.4.0.dist-info/RECORD
