Metadata-Version: 2.4
Name: maap_algorithms_jupyter_extension
Version: 0.4.0
Dynamic: Keywords
Summary: A JupyterLab extension for managing algorithms on the MAAP
Project-URL: Homepage, https://github.com/MAAP-Project/algorithms-jupyter-extension.git
Project-URL: Bug Tracker, https://github.com/MAAP-Project/algorithms_jupyter_extension/issues
Project-URL: Repository, https://github.com/MAAP-Project/algorithms-jupyter-extension
Author-email: Marjorie Lucas <marjorie.j.lucas@jpl.nasa.gov>
License:                                  Apache License
License-File: LICENSE
Classifier: Framework :: Jupyter
Classifier: Framework :: Jupyter :: JupyterLab
Classifier: Framework :: Jupyter :: JupyterLab :: 4
Classifier: Framework :: Jupyter :: JupyterLab :: Extensions
Classifier: Framework :: Jupyter :: JupyterLab :: Extensions :: Prebuilt
Classifier: License :: OSI Approved :: BSD License
Classifier: Programming Language :: Python
Classifier: Programming Language :: Python :: 3
Classifier: Programming Language :: Python :: 3.7
Classifier: Programming Language :: Python :: 3.8
Classifier: Programming Language :: Python :: 3.9
Classifier: Programming Language :: Python :: 3.10
Classifier: Programming Language :: Python :: 3.11
Requires-Python: >=3.8
